gas_0627/__init__.py
gas_0627/switcher.py
gas_0627-1.0.0.dist-info/LICENSE
gas_0627-1.0.0.dist-info/METADATA
gas_0627-1.0.0.dist-info/WHEEL
gas_0627-1.0.0.dist-info/top_level.txt
gas_0627-1.0.0.dist-info/RECORD
